Metadata-Version: 2.1
Name: micro-users
Version: 1.8.4
Summary: Arabic Django user management app with abstract user, permissions, and activity logging
Home-page: https://github.com/debeski/micro-users
Author: DeBeski
Author-email: DeBeski <debeski1@gmail.com>
License: MIT
Project-URL: Homepage, https://github.com/debeski/micro-users
Keywords: django,users,permissions,authentication
Classifier: Framework :: Django
Classifier: Framework :: Django :: 5
Classifier: Programming Language :: Python :: 3
Classifier: Programming Language :: Python :: 3.8
Classifier: Programming Language :: Python :: 3.9
Classifier: Programming Language :: Python :: 3.10
Classifier: Programming Language :: Python :: 3.11
Classifier: Programming Language :: Python :: 3.12
Classifier: Programming Language :: Python :: 3.13
Classifier: Programming Language :: Python :: 3.14
Classifier: License :: OSI Approved :: MIT License
Classifier: Operating System :: OS Independent
Requires-Python: >=3.9
License-File: LICENSE
Requires-Dist: Django (>=5.1)
Requires-Dist: django-crispy-forms (>=2.4)
Requires-Dist: django-tables2 (>=2.7)
Requires-Dist: django-filter (>=24.3)
Requires-Dist: pillow (>=11.0)
Requires-Dist: babel (>=2.1)
